[
  {
    "id": "1ioyh",
    "quote": "Success usually comes to those who are too busy to be looking for it.",
    "author": "-- Henry David Thoreau",
    "image": "assets/.jpg"
  },
  {
    "id": "2ioyh",
    "quote": "Opportunities don't happen. You create them.",
    "author": "-- Chris Grosser",
    "image": "assets/rocket.jpg"
  },
  {
    "id": "3ioyh",
    "quote": "There are two types of people who will tell you that you cannot make a difference in this world: those who are afraid to try and those who are afraid you will succeed.",
    "author": "-- Chris Grosser",
    "image": "assets/thinker.jpg"
  },
  {
    "id": "4ioyh",
    "quote": "Stop chasing the money and start chasing the passion.",
    "author": "-- Chris Grosser",
    "image": "assets/thinker.jpg"
  },
  {
    "id": "5ioyh",
    "quote": "All progress takes place outside the comfort zone.",
    "author": "-- Chris Grosser",
    "image": "assets/thinker.jpg"
  },
  {
    "id": "6ioyh",
    "quote": "If you really look closely, most overnight successes took a long time.",
    "author": "-- Chris Grosser",
    "image": "assets/thinker.jpg"
  },
  {
    "id": "7ioyh",
    "quote": "The only limit to our realization of tomorrow will be our doubts of today.",
    "author": "-- Chris Grosser",
    "image": "assets/thinker.jpg"
  },
  {
    "id": "8ioyh",
    "quote": "The way to get started is to quit talking and begin doing.",
    "author": "-- Chris Grosser",
    "image": "assets/thinker.jpg"
  },
  {
    "id": "9ioyh",
    "quote": "The successful warrior is the average man, with laser-like focus",
    "author": "-- Chris Grosser",
    "image": "assets/thinker.jpg"
  },
  {
    "id": "10ioyh",
    "quote": "The only place where success comes before work is in the dictionary.",
    "author": "-- Vince Lombardi",
    "image": "assets/Vince-Lombardi.jpg"
  }
]
